nptel_dl.py
nptel_dl-1.10.dist-info/LICENSE
nptel_dl-1.10.dist-info/METADATA
nptel_dl-1.10.dist-info/WHEEL
nptel_dl-1.10.dist-info/entry_points.txt
nptel_dl-1.10.dist-info/top_level.txt
nptel_dl-1.10.dist-info/zip-safe
nptel_dl-1.10.dist-info/RECORD
