Metadata-Version: 2.1
Name: nptel-dl
Version: 1.10
Summary: Downloader for NPTEL
Home-page: https://github.com/deshdeepak1/nptel-dl
Author: Deshdeepak
Author-email: rkdeshdeepak1@gmail.com
License: MIT
Keywords: nptel NPTEL dl download downloader
Platform: UNKNOWN
Classifier: Programming Language :: Python :: 3
Classifier: License :: OSI Approved :: MIT License
Classifier: Operating System :: OS Independent
Requires-Dist: bs4
Requires-Dist: requests
Requires-Dist: gdown
Requires-Dist: yt-dlp
